{"GlobalPropertiesHash":"Cc/FcS1fHQ7ePBQhDlU3e/aCj35/UaqEOHm4bSdCJHQ=","FingerprintPatternsHash":"gq3WsqcKBUGTSNle7RKKyXRIwh7M8ccEqOqYvIzoM04=","PropertyOverridesHash":"8ZRc1sGeVrPBx4lD717BgRaQekyh78QKV9SKsdt638U=","InputHashes":["uaOJtUZ07zXMw7c4bk7tQ3hlPq47rWgZTjWzqnE44OE=","NKkQ4PF5HF/4xiSW2QMpt5iXerzoECnbzJDY8YHNr2A=","zrPy\u002BV9AsrisnRq7RUpZG3XJKgDPhb\u002BK8sBj0xLzuGg=","jLO3fcPeBK159ZCstO2GJj/2aw2T/PyA/LZHWL48nH0=","dSIKVpGQ\u002BQ6l\u002B1apA6cP8Bc5GFSWo0ep0OggIDN87aQ=","xOycOTT7NsU6PIu5sm6kjmFM37TXqBMoTHSdY5KOArU="],"CachedAssets":{"uaOJtUZ07zXMw7c4bk7tQ3hlPq47rWgZTjWzqnE44OE=":{"Identity":"D:\\WEB API\\WebApiShop\\WebApiShop\\wwwroot\\index.html","SourceId":"WebApiShop","SourceType":"Discovered","ContentRoot":"D:\\WEB API\\WebApiShop\\WebApiShop\\wwwroot\\","BasePath":"_content/WebApiShop","RelativePath":"index#[.{fingerprint}]?.html","AssetKind":"All","AssetMode":"All","AssetRole":"Primary","AssetMergeBehavior":null,"AssetMergeSource":"","RelatedAsset":null,"AssetTraitName":null,"AssetTraitValue":null,"Fingerprint":"8mrbbri5sq","Integrity":"kPdLJPLNQHlfG9dx/BVjB1QJcgsBQAtaBgiaVFCN6gU=","CopyToOutputDirectory":"Never","CopyToPublishDirectory":"PreserveNewest","OriginalItemSpec":"wwwroot\\index.html","FileLength":4150,"LastWriteTime":"2025-10-26T16:52:40+00:00"},"NKkQ4PF5HF/4xiSW2QMpt5iXerzoECnbzJDY8YHNr2A=":{"Identity":"D:\\WEB API\\WebApiShop\\WebApiShop\\wwwroot\\index.js","SourceId":"WebApiShop","SourceType":"Discovered","ContentRoot":"D:\\WEB API\\WebApiShop\\WebApiShop\\wwwroot\\","BasePath":"_content/WebApiShop","RelativePath":"index#[.{fingerprint}]?.js","AssetKind":"All","AssetMode":"All","AssetRole":"Primary","AssetMergeBehavior":null,"AssetMergeSource":"","RelatedAsset":null,"AssetTraitName":null,"AssetTraitValue":null,"Fingerprint":"pf97oow1pz","Integrity":"exwfJdMbdAHdRZFa5Bh8Igkfju1H6AMc99kYJR8/AW4=","CopyToOutputDirectory":"Never","CopyToPublishDirectory":"PreserveNewest","OriginalItemSpec":"wwwroot\\index.js","FileLength":2503,"LastWriteTime":"2025-10-26T16:52:44+00:00"},"zrPy\u002BV9AsrisnRq7RUpZG3XJKgDPhb\u002BK8sBj0xLzuGg=":{"Identity":"D:\\WEB API\\WebApiShop\\WebApiShop\\wwwroot\\UpDateDetails.js","SourceId":"WebApiShop","SourceType":"Discovered","ContentRoot":"D:\\WEB API\\WebApiShop\\WebApiShop\\wwwroot\\","BasePath":"_content/WebApiShop","RelativePath":"UpDateDetails#[.{fingerprint}]?.js","AssetKind":"All","AssetMode":"All","AssetRole":"Primary","AssetMergeBehavior":null,"AssetMergeSource":"","RelatedAsset":null,"AssetTraitName":null,"AssetTraitValue":null,"Fingerprint":"8njgwwnqzk","Integrity":"jKjbKwxPZsrYlMNHVgIVNxGJituZDzGhwovWtWvtmxc=","CopyToOutputDirectory":"Never","CopyToPublishDirectory":"PreserveNewest","OriginalItemSpec":"wwwroot\\UpDateDetails.js","FileLength":1928,"LastWriteTime":"2025-10-26T16:52:46+00:00"},"jLO3fcPeBK159ZCstO2GJj/2aw2T/PyA/LZHWL48nH0=":{"Identity":"D:\\WEB API\\WebApiShop\\WebApiShop\\wwwroot\\UserDetails.html","SourceId":"WebApiShop","SourceType":"Discovered","ContentRoot":"D:\\WEB API\\WebApiShop\\WebApiShop\\wwwroot\\","BasePath":"_content/WebApiShop","RelativePath":"UserDetails#[.{fingerprint}]?.html","AssetKind":"All","AssetMode":"All","AssetRole":"Primary","AssetMergeBehavior":null,"AssetMergeSource":"","RelatedAsset":null,"AssetTraitName":null,"AssetTraitValue":null,"Fingerprint":"0lns9ddtpx","Integrity":"nIwcilG3XkfToiZGf\u002BOFBRGaZ5ENwez\u002B8yaYwLrLAfs=","CopyToOutputDirectory":"Never","CopyToPublishDirectory":"PreserveNewest","OriginalItemSpec":"wwwroot\\UserDetails.html","FileLength":3430,"LastWriteTime":"2025-10-26T16:52:50+00:00"}},"CachedCopyCandidates":{}}